rabbitman.py
rabbitman-0.1.0.dist-info/DESCRIPTION.rst
rabbitman-0.1.0.dist-info/METADATA
rabbitman-0.1.0.dist-info/metadata.json
rabbitman-0.1.0.dist-info/RECORD
rabbitman-0.1.0.dist-info/top_level.txt
rabbitman-0.1.0.dist-info/WHEEL
