Metadata-Version: 2.0
Name: rabbitman
Version: 0.1.0
Summary: Python interface to the RabbitMQ management api
Home-page: https://github.com/davidszotten/rabbitman
Author: David Szotten
Author-email: davidszotten@gmail.com
License: MIT
Platform: UNKNOWN
Classifier: Development Status :: 3 - Alpha
Classifier: Intended Audience :: Developers
Classifier: License :: OSI Approved :: MIT License
Classifier: Programming Language :: Python :: 2
Classifier: Programming Language :: Python :: 2.7
Classifier: Programming Language :: Python :: 3
Classifier: Programming Language :: Python :: 3.4
Requires-Dist: requests
Provides-Extra: codegen
Requires-Dist: html2rst; extra == 'codegen'
